{
  "investigation": {
    "id": "OSD-155",
    "title": "",
    "description": "",
    "mission": {
      "name": "",
      "start_date": "",
      "end_date": "",
      "link": ""
    },
    "project": {
      "identifier": "",
      "title": "",
      "type": "",
      "link": "",
      "funding": "",
      "managing_center": ""
    },
    "protocols": [],
    "publications": [],
    "factors": [],
    "contacts": []
  },
  "study": {
    "samples": [
      {
        "sample_name": "GSM575992 extract 1",
        "characteristics": {
          "Organism": "Homo sapiens",
          "Material Type": "Whole Blood",
          "Donor": "MSm4",
          "Sex": "Male",
          "age": "28"
        },
        "factors": {
          "Smoking Status": "smoker",
          "Ionizing Radiation": "cesium-137 gamma radiation",
          "Absorbed Radiation Dose": "0.5"
        },
        "parameters": {
          "ionizing radiation energy": "0.662",
          "absorbed radiation dose rate": "0.82",
          "exposure duration": "0.61",
          "ionizing radiation categorized by source": "gamma irradiator",
          "ionizing radiation device": "Gammacell 40"
        },
        "comments": {}
      },
      {
        "sample_name": "GSM575944 extract 1",
        "characteristics": {
          "Organism": "Homo sapiens",
          "Material Type": "Whole Blood",
          "Donor": "FSm4",
          "Sex": "Female",
          "age": "55"
        },
        "factors": {
          "Smoking Status": "smoker",
          "Ionizing Radiation": "cesium-137 gamma radiation",
          "Absorbed Radiation Dose": "0.1"
        },
        "parameters": {
          "ionizing radiation energy": "0.662",
          "absorbed radiation dose rate": "0.82",
          "exposure duration": "0.12",
          "ionizing radiation categorized by source": "gamma irradiator",
          "ionizing radiation device": "Gammacell 40"
        },
        "comments": {}
      },
      {
        "sample_name": "GSM575934 extract 1",
        "characteristics": {
          "Organism": "Homo sapiens",
          "Material Type": "Whole Blood",
          "Donor": "FSm1",
          "Sex": "Female",
          "age": "32"
        },
        "factors": {
          "Smoking Status": "smoker",
          "Ionizing Radiation": "sham-irradiated",
          "Absorbed Radiation Dose": "0"
        },
        "parameters": {
          "ionizing radiation energy": "",
          "absorbed radiation dose rate": "",
          "exposure duration": "",
          "ionizing radiation categorized by source": "",
          "ionizing radiation device": ""
        },
        "comments": {}
      },
      {
        "sample_name": "GSM575980 extract 1",
        "characteristics": {
          "Organism": "Homo sapiens",
          "Material Type": "Whole Blood",
          "Donor": "MSm1",
          "Sex": "Male",
          "age": "41"
        },
        "factors": {
          "Smoking Status": "smoker",
          "Ionizing Radiation": "cesium-137 gamma radiation",
          "Absorbed Radiation Dose": "0.5"
        },
        "parameters": {
          "ionizing radiation energy": "0.662",
          "absorbed radiation dose rate": "0.82",
          "exposure duration": "0.61",
          "ionizing radiation categorized by source": "gamma irradiator",
          "ionizing radiation device": "Gammacell 40"
        },
        "comments": {}
      },
      {
        "sample_name": "GSM575962 extract 1",
        "characteristics": {
          "Organism": "Homo sapiens",
          "Material Type": "Whole Blood",
          "Donor": "MNs2",
          "Sex": "Male",
          "age": "38"
        },
        "factors": {
          "Smoking Status": "non-smoker",
          "Ionizing Radiation": "cesium-137 gamma radiation",
          "Absorbed Radiation Dose": "2"
        },
        "parameters": {
          "ionizing radiation energy": "0.662",
          "absorbed radiation dose rate": "0.82",
          "exposure duration": "2.44",
          "ionizing radiation categorized by source": "gamma irradiator",
          "ionizing radiation device": "Gammacell 40"
        },
        "comments": {}
      },
      {
        "sample_name": "GSM575990 extract 1",
        "characteristics": {
          "Organism": "Homo sapiens",
          "Material Type": "Whole Blood",
          "Donor": "MSm3",
          "Sex": "Male",
          "age": "52"
        },
        "factors": {
          "Smoking Status": "smoker",
          "Ionizing Radiation": "cesium-137 gamma radiation",
          "Absorbed Radiation Dose": "2"
        },
        "parameters": {
          "ionizing radiation energy": "0.662",
          "absorbed radiation dose rate": "0.82",
          "exposure duration": "2.44",
          "ionizing radiation categorized by source": "gamma irradiator",
          "ionizing radiation device": "Gammacell 40"
        },
        "comments": {}
      },
      {
        "sample_name": "GSM575933 extract 1",
        "characteristics": {
          "Organism": "Homo sapiens",
          "Material Type": "Whole Blood",
          "Donor": "FSm1",
          "Sex": "Female",
          "age": "32"
        },
        "factors": {
          "Smoking Status": "smoker",
          "Ionizing Radiation": "cesium-137 gamma radiation",
          "Absorbed Radiation Dose": "0.5"
        },
        "parameters": {
          "ionizing radiation energy": "0.662",
          "absorbed radiation dose rate": "0.82",
          "exposure duration": "0.61",
          "ionizing radiation categorized by source": "gamma irradiator",
          "ionizing radiation device": "Gammacell 40"
        },
        "comments": {}
      },
      {
        "sample_name": "GSM575930 extract 1",
        "characteristics": {
          "Organism": "Homo sapiens",
          "Material Type": "Whole Blood",
          "Donor": "FNs6",
          "Sex": "Female",
          "age": "21"
        },
        "factors": {
          "Smoking Status": "non-smoker",
          "Ionizing Radiation": "sham-irradiated",
          "Absorbed Radiation Dose": "0"
        },
        "parameters": {
          "ionizing radiation energy": "",
          "absorbed radiation dose rate": "",
          "exposure duration": "",
          "ionizing radiation categorized by source": "",
          "ionizing radiation device": ""
        },
        "comments": {}
      },
      {
        "sample_name": "GSM575916 extract 1",
        "characteristics": {
          "Organism": "Homo sapiens",
          "Material Type": "Whole Blood",
          "Donor": "FNs3",
          "Sex": "Female",
          "age": "24"
        },
        "factors": {
          "Smoking Status": "non-smoker",
          "Ionizing Radiation": "cesium-137 gamma radiation",
          "Absorbed Radiation Dose": "0.1"
        },
        "parameters": {
          "ionizing radiation energy": "0.662",
          "absorbed radiation dose rate": "0.82",
          "exposure duration": "0.12",
          "ionizing radiation categorized by source": "gamma irradiator",
          "ionizing radiation device": "Gammacell 40"
        },
        "comments": {}
      },
      {
        "sample_name": "GSM575923 extract 1",
        "characteristics": {
          "Organism": "Homo sapiens",
          "Material Type": "Whole Blood",
          "Donor": "FNs4",
          "Sex": "Female",
          "age": "39"
        },
        "factors": {
          "Smoking Status": "non-smoker",
          "Ionizing Radiation": "cesium-137 gamma radiation",
          "Absorbed Radiation Dose": "2"
        },
        "parameters": {
          "ionizing radiation energy": "0.662",
          "absorbed radiation dose rate": "0.82",
          "exposure duration": "2.44",
          "ionizing radiation categorized by source": "gamma irradiator",
          "ionizing radiation device": "Gammacell 40"
        },
        "comments": {}
      },
      {
        "sample_name": "GSM575952 extract 1",
        "characteristics": {
          "Organism": "Homo sapiens",
          "Material Type": "Whole Blood",
          "Donor": "FSm6",
          "Sex": "Female",
          "age": "54"
        },
        "factors": {
          "Smoking Status": "smoker",
          "Ionizing Radiation": "cesium-137 gamma radiation",
          "Absorbed Radiation Dose": "0.1"
        },
        "parameters": {
          "ionizing radiation energy": "0.662",
          "absorbed radiation dose rate": "0.82",
          "exposure duration": "0.12",
          "ionizing radiation categorized by source": "gamma irradiator",
          "ionizing radiation device": "Gammacell 40"
        },
        "comments": {}
      },
      {
        "sample_name": "GSM575991 extract 1",
        "characteristics": {
          "Organism": "Homo sapiens",
          "Material Type": "Whole Blood",
          "Donor": "MSm4",
          "Sex": "Male",
          "age": "28"
        },
        "factors": {
          "Smoking Status": "smoker",
          "Ionizing Radiation": "cesium-137 gamma radiation",
          "Absorbed Radiation Dose": "0.1"
        },
        "parameters": {
          "ionizing radiation energy": "0.662",
          "absorbed radiation dose rate": "0.82",
          "exposure duration": "0.12",
          "ionizing radiation categorized by source": "gamma irradiator",
          "ionizing radiation device": "Gammacell 40"
        },
        "comments": {}
      },
      {
        "sample_name": "GSM575940 extract 1",
        "characteristics": {
          "Organism": "Homo sapiens",
          "Material Type": "Whole Blood",
          "Donor": "FSm3",
          "Sex": "Female",
          "age": "27"
        },
        "factors": {
          "Smoking Status": "smoker",
          "Ionizing Radiation": "cesium-137 gamma radiation",
          "Absorbed Radiation Dose": "0.1"
        },
        "parameters": {
          "ionizing radiation energy": "0.662",
          "absorbed radiation dose rate": "0.82",
          "exposure duration": "0.12",
          "ionizing radiation categorized by source": "gamma irradiator",
          "ionizing radiation device": "Gammacell 40"
        },
        "comments": {}
      },
      {
        "sample_name": "GSM575914 extract 1",
        "characteristics": {
          "Organism": "Homo sapiens",
          "Material Type": "Whole Blood",
          "Donor": "FNs2",
          "Sex": "Female",
          "age": "35"
        },
        "factors": {
          "Smoking Status": "non-smoker",
          "Ionizing Radiation": "sham-irradiated",
          "Absorbed Radiation Dose": "0"
        },
        "parameters": {
          "ionizing radiation energy": "",
          "absorbed radiation dose rate": "",
          "exposure duration": "",
          "ionizing radiation categorized by source": "",
          "ionizing radiation device": ""
        },
        "comments": {}
      },
      {
        "sample_name": "GSM575920 extract 1",
        "characteristics": {
          "Organism": "Homo sapiens",
          "Material Type": "Whole Blood",
          "Donor": "FNs4",
          "Sex": "Female",
          "age": "39"
        },
        "factors": {
          "Smoking Status": "non-smoker",
          "Ionizing Radiation": "cesium-137 gamma radiation",
          "Absorbed Radiation Dose": "0.1"
        },
        "parameters": {
          "ionizing radiation energy": "0.662",
          "absorbed radiation dose rate": "0.82",
          "exposure duration": "0.12",
          "ionizing radiation categorized by source": "gamma irradiator",
          "ionizing radiation device": "Gammacell 40"
        },
        "comments": {}
      },
      {
        "sample_name": "GSM575942 extract 1",
        "characteristics": {
          "Organism": "Homo sapiens",
          "Material Type": "Whole Blood",
          "Donor": "FSm3",
          "Sex": "Female",
          "age": "27"
        },
        "factors": {
          "Smoking Status": "smoker",
          "Ionizing Radiation": "sham-irradiated",
          "Absorbed Radiation Dose": "0"
        },
        "parameters": {
          "ionizing radiation energy": "",
          "absorbed radiation dose rate": "",
          "exposure duration": "",
          "ionizing radiation categorized by source": "",
          "ionizing radiation device": ""
        },
        "comments": {}
      },
      {
        "sample_name": "GSM575924 extract 1",
        "characteristics": {
          "Organism": "Homo sapiens",
          "Material Type": "Whole Blood",
          "Donor": "FNs5",
          "Sex": "Female",
          "age": "40"
        },
        "factors": {
          "Smoking Status": "non-smoker",
          "Ionizing Radiation": "cesium-137 gamma radiation",
          "Absorbed Radiation Dose": "0.1"
        },
        "parameters": {
          "ionizing radiation energy": "0.662",
          "absorbed radiation dose rate": "0.82",
          "exposure duration": "0.12",
          "ionizing radiation categorized by source": "gamma irradiator",
          "ionizing radiation device": "Gammacell 40"
        },
        "comments": {}
      },
      {
        "sample_name": "GSM575913 extract 1",
        "characteristics": {
          "Organism": "Homo sapiens",
          "Material Type": "Whole Blood",
          "Donor": "FNs2",
          "Sex": "Female",
          "age": "35"
        },
        "factors": {
          "Smoking Status": "non-smoker",
          "Ionizing Radiation": "cesium-137 gamma radiation",
          "Absorbed Radiation Dose": "0.5"
        },
        "parameters": {
          "ionizing radiation energy": "0.662",
          "absorbed radiation dose rate": "0.82",
          "exposure duration": "0.61",
          "ionizing radiation categorized by source": "gamma irradiator",
          "ionizing radiation device": "Gammacell 40"
        },
        "comments": {}
      },
      {
        "sample_name": "GSM575997 extract 1",
        "characteristics": {
          "Organism": "Homo sapiens",
          "Material Type": "Whole Blood",
          "Donor": "MSm5",
          "Sex": "Male",
          "age": "59"
        },
        "factors": {
          "Smoking Status": "smoker",
          "Ionizing Radiation": "sham-irradiated",
          "Absorbed Radiation Dose": "0"
        },
        "parameters": {
          "ionizing radiation energy": "",
          "absorbed radiation dose rate": "",
          "exposure duration": "",
          "ionizing radiation categorized by source": "",
          "ionizing radiation device": ""
        },
        "comments": {}
      },
      {
        "sample_name": "GSM575965 extract 1",
        "characteristics": {
          "Organism": "Homo sapiens",
          "Material Type": "Whole Blood",
          "Donor": "MNs3",
          "Sex": "Male",
          "age": "31"
        },
        "factors": {
          "Smoking Status": "non-smoker",
          "Ionizing Radiation": "sham-irradiated",
          "Absorbed Radiation Dose": "0"
        },
        "parameters": {
          "ionizing radiation energy": "",
          "absorbed radiation dose rate": "",
          "exposure duration": "",
          "ionizing radiation categorized by source": "",
          "ionizing radiation device": ""
        },
        "comments": {}
      },
      {
        "sample_name": "GSM575969 extract 1",
        "characteristics": {
          "Organism": "Homo sapiens",
          "Material Type": "Whole Blood",
          "Donor": "MNs4",
          "Sex": "Male",
          "age": "52"
        },
        "factors": {
          "Smoking Status": "non-smoker",
          "Ionizing Radiation": "sham-irradiated",
          "Absorbed Radiation Dose": "0"
        },
        "parameters": {
          "ionizing radiation energy": "",
          "absorbed radiation dose rate": "",
          "exposure duration": "",
          "ionizing radiation categorized by source": "",
          "ionizing radiation device": ""
        },
        "comments": {}
      },
      {
        "sample_name": "GSM575984 extract 1",
        "characteristics": {
          "Organism": "Homo sapiens",
          "Material Type": "Whole Blood",
          "Donor": "MSm2",
          "Sex": "Male",
          "age": "31"
        },
        "factors": {
          "Smoking Status": "smoker",
          "Ionizing Radiation": "cesium-137 gamma radiation",
          "Absorbed Radiation Dose": "0.5"
        },
        "parameters": {
          "ionizing radiation energy": "0.662",
          "absorbed radiation dose rate": "0.82",
          "exposure duration": "0.61",
          "ionizing radiation categorized by source": "gamma irradiator",
          "ionizing radiation device": "Gammacell 40"
        },
        "comments": {}
      },
      {
        "sample_name": "GSM575960 extract 1",
        "characteristics": {
          "Organism": "Homo sapiens",
          "Material Type": "Whole Blood",
          "Donor": "MNs2",
          "Sex": "Male",
          "age": "38"
        },
        "factors": {
          "Smoking Status": "non-smoker",
          "Ionizing Radiation": "cesium-137 gamma radiation",
          "Absorbed Radiation Dose": "0.5"
        },
        "parameters": {
          "ionizing radiation energy": "0.662",
          "absorbed radiation dose rate": "0.82",
          "exposure duration": "0.61",
          "ionizing radiation categorized by source": "gamma irradiator",
          "ionizing radiation device": "Gammacell 40"
        },
        "comments": {}
      },
      {
        "sample_name": "GSM575967 extract 1",
        "characteristics": {
          "Organism": "Homo sapiens",
          "Material Type": "Whole Blood",
          "Donor": "MNs4",
          "Sex": "Male",
          "age": "52"
        },
        "factors": {
          "Smoking Status": "non-smoker",
          "Ionizing Radiation": "cesium-137 gamma radiation",
          "Absorbed Radiation Dose": "0.1"
        },
        "parameters": {
          "ionizing radiation energy": "0.662",
          "absorbed radiation dose rate": "0.82",
          "exposure duration": "0.12",
          "ionizing radiation categorized by source": "gamma irradiator",
          "ionizing radiation device": "Gammacell 40"
        },
        "comments": {}
      },
      {
        "sample_name": "GSM575939 extract 1",
        "characteristics": {
          "Organism": "Homo sapiens",
          "Material Type": "Whole Blood",
          "Donor": "FSm2",
          "Sex": "Female",
          "age": "35"
        },
        "factors": {
          "Smoking Status": "smoker",
          "Ionizing Radiation": "cesium-137 gamma radiation",
          "Absorbed Radiation Dose": "2"
        },
        "parameters": {
          "ionizing radiation energy": "0.662",
          "absorbed radiation dose rate": "0.82",
          "exposure duration": "2.44",
          "ionizing radiation categorized by source": "gamma irradiator",
          "ionizing radiation device": "Gammacell 40"
        },
        "comments": {}
      },
      {
        "sample_name": "GSM575983 extract 1",
        "characteristics": {
          "Organism": "Homo sapiens",
          "Material Type": "Whole Blood",
          "Donor": "MSm2",
          "Sex": "Male",
          "age": "31"
        },
        "factors": {
          "Smoking Status": "smoker",
          "Ionizing Radiation": "cesium-137 gamma radiation",
          "Absorbed Radiation Dose": "0.1"
        },
        "parameters": {
          "ionizing radiation energy": "0.662",
          "absorbed radiation dose rate": "0.82",
          "exposure duration": "0.12",
          "ionizing radiation categorized by source": "gamma irradiator",
          "ionizing radiation device": "Gammacell 40"
        },
        "comments": {}
      },
      {
        "sample_name": "GSM575935 extract 1",
        "characteristics": {
          "Organism": "Homo sapiens",
          "Material Type": "Whole Blood",
          "Donor": "FSm1",
          "Sex": "Female",
          "age": "32"
        },
        "factors": {
          "Smoking Status": "smoker",
          "Ionizing Radiation": "cesium-137 gamma radiation",
          "Absorbed Radiation Dose": "2"
        },
        "parameters": {
          "ionizing radiation energy": "0.662",
          "absorbed radiation dose rate": "0.82",
          "exposure duration": "2.44",
          "ionizing radiation categorized by source": "gamma irradiator",
          "ionizing radiation device": "Gammacell 40"
        },
        "comments": {}
      },
      {
        "sample_name": "GSM575971 extract 1",
        "characteristics": {
          "Organism": "Homo sapiens",
          "Material Type": "Whole Blood",
          "Donor": "MNs5",
          "Sex": "Male",
          "age": "23"
        },
        "factors": {
          "Smoking Status": "non-smoker",
          "Ionizing Radiation": "cesium-137 gamma radiation",
          "Absorbed Radiation Dose": "0.1"
        },
        "parameters": {
          "ionizing radiation energy": "0.662",
          "absorbed radiation dose rate": "0.82",
          "exposure duration": "0.12",
          "ionizing radiation categorized by source": "gamma irradiator",
          "ionizing radiation device": "Gammacell 40"
        },
        "comments": {}
      },
      {
        "sample_name": "GSM575951 extract 1",
        "characteristics": {
          "Organism": "Homo sapiens",
          "Material Type": "Whole Blood",
          "Donor": "FSm5",
          "Sex": "Female",
          "age": "29"
        },
        "factors": {
          "Smoking Status": "smoker",
          "Ionizing Radiation": "cesium-137 gamma radiation",
          "Absorbed Radiation Dose": "2"
        },
        "parameters": {
          "ionizing radiation energy": "0.662",
          "absorbed radiation dose rate": "0.82",
          "exposure duration": "2.44",
          "ionizing radiation categorized by source": "gamma irradiator",
          "ionizing radiation device": "Gammacell 40"
        },
        "comments": {}
      },
      {
        "sample_name": "GSM575973 extract 1",
        "characteristics": {
          "Organism": "Homo sapiens",
          "Material Type": "Whole Blood",
          "Donor": "MNs5",
          "Sex": "Male",
          "age": "23"
        },
        "factors": {
          "Smoking Status": "non-smoker",
          "Ionizing Radiation": "sham-irradiated",
          "Absorbed Radiation Dose": "0"
        },
        "parameters": {
          "ionizing radiation energy": "",
          "absorbed radiation dose rate": "",
          "exposure duration": "",
          "ionizing radiation categorized by source": "",
          "ionizing radiation device": ""
        },
        "comments": {}
      },
      {
        "sample_name": "GSM575929 extract 1",
        "characteristics": {
          "Organism": "Homo sapiens",
          "Material Type": "Whole Blood",
          "Donor": "FNs6",
          "Sex": "Female",
          "age": "21"
        },
        "factors": {
          "Smoking Status": "non-smoker",
          "Ionizing Radiation": "cesium-137 gamma radiation",
          "Absorbed Radiation Dose": "0.5"
        },
        "parameters": {
          "ionizing radiation energy": "0.662",
          "absorbed radiation dose rate": "0.82",
          "exposure duration": "0.61",
          "ionizing radiation categorized by source": "gamma irradiator",
          "ionizing radiation device": "Gammacell 40"
        },
        "comments": {}
      },
      {
        "sample_name": "GSM575955 extract 1",
        "characteristics": {
          "Organism": "Homo sapiens",
          "Material Type": "Whole Blood",
          "Donor": "MNs1",
          "Sex": "Male",
          "age": "29"
        },
        "factors": {
          "Smoking Status": "non-smoker",
          "Ionizing Radiation": "cesium-137 gamma radiation",
          "Absorbed Radiation Dose": "0.1"
        },
        "parameters": {
          "ionizing radiation energy": "0.662",
          "absorbed radiation dose rate": "0.82",
          "exposure duration": "0.12",
          "ionizing radiation categorized by source": "gamma irradiator",
          "ionizing radiation device": "Gammacell 40"
        },
        "comments": {}
      },
      {
        "sample_name": "GSM575915 extract 1",
        "characteristics": {
          "Organism": "Homo sapiens",
          "Material Type": "Whole Blood",
          "Donor": "FNs2",
          "Sex": "Female",
          "age": "35"
        },
        "factors": {
          "Smoking Status": "non-smoker",
          "Ionizing Radiation": "cesium-137 gamma radiation",
          "Absorbed Radiation Dose": "2"
        },
        "parameters": {
          "ionizing radiation energy": "0.662",
          "absorbed radiation dose rate": "0.82",
          "exposure duration": "2.44",
          "ionizing radiation categorized by source": "gamma irradiator",
          "ionizing radiation device": "Gammacell 40"
        },
        "comments": {}
      },
      {
        "sample_name": "GSM575932 extract 1",
        "characteristics": {
          "Organism": "Homo sapiens",
          "Material Type": "Whole Blood",
          "Donor": "FSm1",
          "Sex": "Female",
          "age": "32"
        },
        "factors": {
          "Smoking Status": "smoker",
          "Ionizing Radiation": "cesium-137 gamma radiation",
          "Absorbed Radiation Dose": "0.1"
        },
        "parameters": {
          "ionizing radiation energy": "0.662",
          "absorbed radiation dose rate": "0.82",
          "exposure duration": "0.12",
          "ionizing radiation categorized by source": "gamma irradiator",
          "ionizing radiation device": "Gammacell 40"
        },
        "comments": {}
      },
      {
        "sample_name": "GSM575938 extract 1",
        "characteristics": {
          "Organism": "Homo sapiens",
          "Material Type": "Whole Blood",
          "Donor": "FSm2",
          "Sex": "Female",
          "age": "35"
        },
        "factors": {
          "Smoking Status": "smoker",
          "Ionizing Radiation": "sham-irradiated",
          "Absorbed Radiation Dose": "0"
        },
        "parameters": {
          "ionizing radiation energy": "",
          "absorbed radiation dose rate": "",
          "exposure duration": "",
          "ionizing radiation categorized by source": "",
          "ionizing radiation device": ""
        },
        "comments": {}
      },
      {
        "sample_name": "GSM576001 extract 1",
        "characteristics": {
          "Organism": "Homo sapiens",
          "Material Type": "Whole Blood",
          "Donor": "MSm6",
          "Sex": "Male",
          "age": "64"
        },
        "factors": {
          "Smoking Status": "smoker",
          "Ionizing Radiation": "sham-irradiated",
          "Absorbed Radiation Dose": "0"
        },
        "parameters": {
          "ionizing radiation energy": "",
          "absorbed radiation dose rate": "",
          "exposure duration": "",
          "ionizing radiation categorized by source": "",
          "ionizing radiation device": ""
        },
        "comments": {}
      },
      {
        "sample_name": "GSM575989 extract 1",
        "characteristics": {
          "Organism": "Homo sapiens",
          "Material Type": "Whole Blood",
          "Donor": "MSm3",
          "Sex": "Male",
          "age": "52"
        },
        "factors": {
          "Smoking Status": "smoker",
          "Ionizing Radiation": "sham-irradiated",
          "Absorbed Radiation Dose": "0"
        },
        "parameters": {
          "ionizing radiation energy": "",
          "absorbed radiation dose rate": "",
          "exposure duration": "",
          "ionizing radiation categorized by source": "",
          "ionizing radiation device": ""
        },
        "comments": {}
      },
      {
        "sample_name": "GSM575957 extract 1",
        "characteristics": {
          "Organism": "Homo sapiens",
          "Material Type": "Whole Blood",
          "Donor": "MNs1",
          "Sex": "Male",
          "age": "29"
        },
        "factors": {
          "Smoking Status": "non-smoker",
          "Ionizing Radiation": "sham-irradiated",
          "Absorbed Radiation Dose": "0"
        },
        "parameters": {
          "ionizing radiation energy": "",
          "absorbed radiation dose rate": "",
          "exposure duration": "",
          "ionizing radiation categorized by source": "",
          "ionizing radiation device": ""
        },
        "comments": {}
      },
      {
        "sample_name": "GSM575925 extract 1",
        "characteristics": {
          "Organism": "Homo sapiens",
          "Material Type": "Whole Blood",
          "Donor": "FNs5",
          "Sex": "Female",
          "age": "40"
        },
        "factors": {
          "Smoking Status": "non-smoker",
          "Ionizing Radiation": "cesium-137 gamma radiation",
          "Absorbed Radiation Dose": "0.5"
        },
        "parameters": {
          "ionizing radiation energy": "0.662",
          "absorbed radiation dose rate": "0.82",
          "exposure duration": "0.61",
          "ionizing radiation categorized by source": "gamma irradiator",
          "ionizing radiation device": "Gammacell 40"
        },
        "comments": {}
      },
      {
        "sample_name": "GSM575918 extract 1",
        "characteristics": {
          "Organism": "Homo sapiens",
          "Material Type": "Whole Blood",
          "Donor": "FNs3",
          "Sex": "Female",
          "age": "24"
        },
        "factors": {
          "Smoking Status": "non-smoker",
          "Ionizing Radiation": "sham-irradiated",
          "Absorbed Radiation Dose": "0"
        },
        "parameters": {
          "ionizing radiation energy": "",
          "absorbed radiation dose rate": "",
          "exposure duration": "",
          "ionizing radiation categorized by source": "",
          "ionizing radiation device": ""
        },
        "comments": {}
      },
      {
        "sample_name": "GSM575985 extract 1",
        "characteristics": {
          "Organism": "Homo sapiens",
          "Material Type": "Whole Blood",
          "Donor": "MSm2",
          "Sex": "Male",
          "age": "31"
        },
        "factors": {
          "Smoking Status": "smoker",
          "Ionizing Radiation": "sham-irradiated",
          "Absorbed Radiation Dose": "0"
        },
        "parameters": {
          "ionizing radiation energy": "",
          "absorbed radiation dose rate": "",
          "exposure duration": "",
          "ionizing radiation categorized by source": "",
          "ionizing radiation device": ""
        },
        "comments": {}
      },
      {
        "sample_name": "GSM575912 extract 1",
        "characteristics": {
          "Organism": "Homo sapiens",
          "Material Type": "Whole Blood",
          "Donor": "FNs2",
          "Sex": "Female",
          "age": "35"
        },
        "factors": {
          "Smoking Status": "non-smoker",
          "Ionizing Radiation": "cesium-137 gamma radiation",
          "Absorbed Radiation Dose": "0.1"
        },
        "parameters": {
          "ionizing radiation energy": "0.662",
          "absorbed radiation dose rate": "0.82",
          "exposure duration": "0.12",
          "ionizing radiation categorized by source": "gamma irradiator",
          "ionizing radiation device": "Gammacell 40"
        },
        "comments": {}
      },
      {
        "sample_name": "GSM575911 extract 1",
        "characteristics": {
          "Organism": "Homo sapiens",
          "Material Type": "Whole Blood",
          "Donor": "FNs1",
          "Sex": "Female",
          "age": "24"
        },
        "factors": {
          "Smoking Status": "non-smoker",
          "Ionizing Radiation": "cesium-137 gamma radiation",
          "Absorbed Radiation Dose": "2"
        },
        "parameters": {
          "ionizing radiation energy": "0.662",
          "absorbed radiation dose rate": "0.82",
          "exposure duration": "2.44",
          "ionizing radiation categorized by source": "gamma irradiator",
          "ionizing radiation device": "Gammacell 40"
        },
        "comments": {}
      },
      {
        "sample_name": "GSM575994 extract 1",
        "characteristics": {
          "Organism": "Homo sapiens",
          "Material Type": "Whole Blood",
          "Donor": "MSm4",
          "Sex": "Male",
          "age": "28"
        },
        "factors": {
          "Smoking Status": "smoker",
          "Ionizing Radiation": "cesium-137 gamma radiation",
          "Absorbed Radiation Dose": "2"
        },
        "parameters": {
          "ionizing radiation energy": "0.662",
          "absorbed radiation dose rate": "0.82",
          "exposure duration": "2.44",
          "ionizing radiation categorized by source": "gamma irradiator",
          "ionizing radiation device": "Gammacell 40"
        },
        "comments": {}
      },
      {
        "sample_name": "GSM575959 extract 1",
        "characteristics": {
          "Organism": "Homo sapiens",
          "Material Type": "Whole Blood",
          "Donor": "MNs2",
          "Sex": "Male",
          "age": "38"
        },
        "factors": {
          "Smoking Status": "non-smoker",
          "Ionizing Radiation": "cesium-137 gamma radiation",
          "Absorbed Radiation Dose": "0.1"
        },
        "parameters": {
          "ionizing radiation energy": "0.662",
          "absorbed radiation dose rate": "0.82",
          "exposure duration": "0.12",
          "ionizing radiation categorized by source": "gamma irradiator",
          "ionizing radiation device": "Gammacell 40"
        },
        "comments": {}
      },
      {
        "sample_name": "GSM575910 extract 1",
        "characteristics": {
          "Organism": "Homo sapiens",
          "Material Type": "Whole Blood",
          "Donor": "FNs1",
          "Sex": "Female",
          "age": "24"
        },
        "factors": {
          "Smoking Status": "non-smoker",
          "Ionizing Radiation": "sham-irradiated",
          "Absorbed Radiation Dose": "0"
        },
        "parameters": {
          "ionizing radiation energy": "",
          "absorbed radiation dose rate": "",
          "exposure duration": "",
          "ionizing radiation categorized by source": "",
          "ionizing radiation device": ""
        },
        "comments": {}
      },
      {
        "sample_name": "GSM575996 extract 1",
        "characteristics": {
          "Organism": "Homo sapiens",
          "Material Type": "Whole Blood",
          "Donor": "MSm5",
          "Sex": "Male",
          "age": "59"
        },
        "factors": {
          "Smoking Status": "smoker",
          "Ionizing Radiation": "cesium-137 gamma radiation",
          "Absorbed Radiation Dose": "0.5"
        },
        "parameters": {
          "ionizing radiation energy": "0.662",
          "absorbed radiation dose rate": "0.82",
          "exposure duration": "0.61",
          "ionizing radiation categorized by source": "gamma irradiator",
          "ionizing radiation device": "Gammacell 40"
        },
        "comments": {}
      },
      {
        "sample_name": "GSM575917 extract 1",
        "characteristics": {
          "Organism": "Homo sapiens",
          "Material Type": "Whole Blood",
          "Donor": "FNs3",
          "Sex": "Female",
          "age": "24"
        },
        "factors": {
          "Smoking Status": "non-smoker",
          "Ionizing Radiation": "cesium-137 gamma radiation",
          "Absorbed Radiation Dose": "0.5"
        },
        "parameters": {
          "ionizing radiation energy": "0.662",
          "absorbed radiation dose rate": "0.82",
          "exposure duration": "0.61",
          "ionizing radiation categorized by source": "gamma irradiator",
          "ionizing radiation device": "Gammacell 40"
        },
        "comments": {}
      },
      {
        "sample_name": "GSM575976 extract 1",
        "characteristics": {
          "Organism": "Homo sapiens",
          "Material Type": "Whole Blood",
          "Donor": "MNs6",
          "Sex": "Male",
          "age": "41"
        },
        "factors": {
          "Smoking Status": "non-smoker",
          "Ionizing Radiation": "cesium-137 gamma radiation",
          "Absorbed Radiation Dose": "0.5"
        },
        "parameters": {
          "ionizing radiation energy": "0.662",
          "absorbed radiation dose rate": "0.82",
          "exposure duration": "0.61",
          "ionizing radiation categorized by source": "gamma irradiator",
          "ionizing radiation device": "Gammacell 40"
        },
        "comments": {}
      },
      {
        "sample_name": "GSM576000 extract 1",
        "characteristics": {
          "Organism": "Homo sapiens",
          "Material Type": "Whole Blood",
          "Donor": "MSm6",
          "Sex": "Male",
          "age": "64"
        },
        "factors": {
          "Smoking Status": "smoker",
          "Ionizing Radiation": "cesium-137 gamma radiation",
          "Absorbed Radiation Dose": "0.5"
        },
        "parameters": {
          "ionizing radiation energy": "0.662",
          "absorbed radiation dose rate": "0.82",
          "exposure duration": "0.61",
          "ionizing radiation categorized by source": "gamma irradiator",
          "ionizing radiation device": "Gammacell 40"
        },
        "comments": {}
      },
      {
        "sample_name": "GSM575993 extract 1",
        "characteristics": {
          "Organism": "Homo sapiens",
          "Material Type": "Whole Blood",
          "Donor": "MSm4",
          "Sex": "Male",
          "age": "28"
        },
        "factors": {
          "Smoking Status": "smoker",
          "Ionizing Radiation": "sham-irradiated",
          "Absorbed Radiation Dose": "0"
        },
        "parameters": {
          "ionizing radiation energy": "",
          "absorbed radiation dose rate": "",
          "exposure duration": "",
          "ionizing radiation categorized by source": "",
          "ionizing radiation device": ""
        },
        "comments": {}
      },
      {
        "sample_name": "GSM575966 extract 1",
        "characteristics": {
          "Organism": "Homo sapiens",
          "Material Type": "Whole Blood",
          "Donor": "MNs3",
          "Sex": "Male",
          "age": "31"
        },
        "factors": {
          "Smoking Status": "non-smoker",
          "Ionizing Radiation": "cesium-137 gamma radiation",
          "Absorbed Radiation Dose": "2"
        },
        "parameters": {
          "ionizing radiation energy": "0.662",
          "absorbed radiation dose rate": "0.82",
          "exposure duration": "2.44",
          "ionizing radiation categorized by source": "gamma irradiator",
          "ionizing radiation device": "Gammacell 40"
        },
        "comments": {}
      },
      {
        "sample_name": "GSM575995 extract 1",
        "characteristics": {
          "Organism": "Homo sapiens",
          "Material Type": "Whole Blood",
          "Donor": "MSm5",
          "Sex": "Male",
          "age": "59"
        },
        "factors": {
          "Smoking Status": "smoker",
          "Ionizing Radiation": "cesium-137 gamma radiation",
          "Absorbed Radiation Dose": "0.1"
        },
        "parameters": {
          "ionizing radiation energy": "0.662",
          "absorbed radiation dose rate": "0.82",
          "exposure duration": "0.12",
          "ionizing radiation categorized by source": "gamma irradiator",
          "ionizing radiation device": "Gammacell 40"
        },
        "comments": {}
      },
      {
        "sample_name": "GSM575926 extract 1",
        "characteristics": {
          "Organism": "Homo sapiens",
          "Material Type": "Whole Blood",
          "Donor": "FNs5",
          "Sex": "Female",
          "age": "40"
        },
        "factors": {
          "Smoking Status": "non-smoker",
          "Ionizing Radiation": "sham-irradiated",
          "Absorbed Radiation Dose": "0"
        },
        "parameters": {
          "ionizing radiation energy": "",
          "absorbed radiation dose rate": "",
          "exposure duration": "",
          "ionizing radiation categorized by source": "",
          "ionizing radiation device": ""
        },
        "comments": {}
      },
      {
        "sample_name": "GSM575963 extract 1",
        "characteristics": {
          "Organism": "Homo sapiens",
          "Material Type": "Whole Blood",
          "Donor": "MNs3",
          "Sex": "Male",
          "age": "31"
        },
        "factors": {
          "Smoking Status": "non-smoker",
          "Ionizing Radiation": "cesium-137 gamma radiation",
          "Absorbed Radiation Dose": "0.1"
        },
        "parameters": {
          "ionizing radiation energy": "0.662",
          "absorbed radiation dose rate": "0.82",
          "exposure duration": "0.12",
          "ionizing radiation categorized by source": "gamma irradiator",
          "ionizing radiation device": "Gammacell 40"
        },
        "comments": {}
      },
      {
        "sample_name": "GSM575999 extract 1",
        "characteristics": {
          "Organism": "Homo sapiens",
          "Material Type": "Whole Blood",
          "Donor": "MSm6",
          "Sex": "Male",
          "age": "64"
        },
        "factors": {
          "Smoking Status": "smoker",
          "Ionizing Radiation": "cesium-137 gamma radiation",
          "Absorbed Radiation Dose": "0.1"
        },
        "parameters": {
          "ionizing radiation energy": "0.662",
          "absorbed radiation dose rate": "0.82",
          "exposure duration": "0.12",
          "ionizing radiation categorized by source": "gamma irradiator",
          "ionizing radiation device": "Gammacell 40"
        },
        "comments": {}
      },
      {
        "sample_name": "GSM575982 extract 1",
        "characteristics": {
          "Organism": "Homo sapiens",
          "Material Type": "Whole Blood",
          "Donor": "MSm1",
          "Sex": "Male",
          "age": "41"
        },
        "factors": {
          "Smoking Status": "smoker",
          "Ionizing Radiation": "cesium-137 gamma radiation",
          "Absorbed Radiation Dose": "2"
        },
        "parameters": {
          "ionizing radiation energy": "0.662",
          "absorbed radiation dose rate": "0.82",
          "exposure duration": "2.44",
          "ionizing radiation categorized by source": "gamma irradiator",
          "ionizing radiation device": "Gammacell 40"
        },
        "comments": {}
      },
      {
        "sample_name": "GSM575981 extract 1",
        "characteristics": {
          "Organism": "Homo sapiens",
          "Material Type": "Whole Blood",
          "Donor": "MSm1",
          "Sex": "Male",
          "age": "41"
        },
        "factors": {
          "Smoking Status": "smoker",
          "Ionizing Radiation": "sham-irradiated",
          "Absorbed Radiation Dose": "0"
        },
        "parameters": {
          "ionizing radiation energy": "",
          "absorbed radiation dose rate": "",
          "exposure duration": "",
          "ionizing radiation categorized by source": "",
          "ionizing radiation device": ""
        },
        "comments": {}
      },
      {
        "sample_name": "GSM575947 extract 1",
        "characteristics": {
          "Organism": "Homo sapiens",
          "Material Type": "Whole Blood",
          "Donor": "FSm4",
          "Sex": "Female",
          "age": "55"
        },
        "factors": {
          "Smoking Status": "smoker",
          "Ionizing Radiation": "cesium-137 gamma radiation",
          "Absorbed Radiation Dose": "2"
        },
        "parameters": {
          "ionizing radiation energy": "0.662",
          "absorbed radiation dose rate": "0.82",
          "exposure duration": "2.44",
          "ionizing radiation categorized by source": "gamma irradiator",
          "ionizing radiation device": "Gammacell 40"
        },
        "comments": {}
      },
      {
        "sample_name": "GSM575908 extract 1",
        "characteristics": {
          "Organism": "Homo sapiens",
          "Material Type": "Whole Blood",
          "Donor": "FNs1",
          "Sex": "Female",
          "age": "24"
        },
        "factors": {
          "Smoking Status": "non-smoker",
          "Ionizing Radiation": "cesium-137 gamma radiation",
          "Absorbed Radiation Dose": "0.1"
        },
        "parameters": {
          "ionizing radiation energy": "0.662",
          "absorbed radiation dose rate": "0.82",
          "exposure duration": "0.12",
          "ionizing radiation categorized by source": "gamma irradiator",
          "ionizing radiation device": "Gammacell 40"
        },
        "comments": {}
      },
      {
        "sample_name": "GSM575919 extract 1",
        "characteristics": {
          "Organism": "Homo sapiens",
          "Material Type": "Whole Blood",
          "Donor": "FNs3",
          "Sex": "Female",
          "age": "24"
        },
        "factors": {
          "Smoking Status": "non-smoker",
          "Ionizing Radiation": "cesium-137 gamma radiation",
          "Absorbed Radiation Dose": "2"
        },
        "parameters": {
          "ionizing radiation energy": "0.662",
          "absorbed radiation dose rate": "0.82",
          "exposure duration": "2.44",
          "ionizing radiation categorized by source": "gamma irradiator",
          "ionizing radiation device": "Gammacell 40"
        },
        "comments": {}
      },
      {
        "sample_name": "GSM575945 extract 1",
        "characteristics": {
          "Organism": "Homo sapiens",
          "Material Type": "Whole Blood",
          "Donor": "FSm4",
          "Sex": "Female",
          "age": "55"
        },
        "factors": {
          "Smoking Status": "smoker",
          "Ionizing Radiation": "cesium-137 gamma radiation",
          "Absorbed Radiation Dose": "0.5"
        },
        "parameters": {
          "ionizing radiation energy": "0.662",
          "absorbed radiation dose rate": "0.82",
          "exposure duration": "0.61",
          "ionizing radiation categorized by source": "gamma irradiator",
          "ionizing radiation device": "Gammacell 40"
        },
        "comments": {}
      },
      {
        "sample_name": "GSM575964 extract 1",
        "characteristics": {
          "Organism": "Homo sapiens",
          "Material Type": "Whole Blood",
          "Donor": "MNs3",
          "Sex": "Male",
          "age": "31"
        },
        "factors": {
          "Smoking Status": "non-smoker",
          "Ionizing Radiation": "cesium-137 gamma radiation",
          "Absorbed Radiation Dose": "0.5"
        },
        "parameters": {
          "ionizing radiation energy": "0.662",
          "absorbed radiation dose rate": "0.82",
          "exposure duration": "0.61",
          "ionizing radiation categorized by source": "gamma irradiator",
          "ionizing radiation device": "Gammacell 40"
        },
        "comments": {}
      },
      {
        "sample_name": "GSM575974 extract 1",
        "characteristics": {
          "Organism": "Homo sapiens",
          "Material Type": "Whole Blood",
          "Donor": "MNs5",
          "Sex": "Male",
          "age": "23"
        },
        "factors": {
          "Smoking Status": "non-smoker",
          "Ionizing Radiation": "cesium-137 gamma radiation",
          "Absorbed Radiation Dose": "2"
        },
        "parameters": {
          "ionizing radiation energy": "0.662",
          "absorbed radiation dose rate": "0.82",
          "exposure duration": "2.44",
          "ionizing radiation categorized by source": "gamma irradiator",
          "ionizing radiation device": "Gammacell 40"
        },
        "comments": {}
      },
      {
        "sample_name": "GSM575977 extract 1",
        "characteristics": {
          "Organism": "Homo sapiens",
          "Material Type": "Whole Blood",
          "Donor": "MNs6",
          "Sex": "Male",
          "age": "41"
        },
        "factors": {
          "Smoking Status": "non-smoker",
          "Ionizing Radiation": "sham-irradiated",
          "Absorbed Radiation Dose": "0"
        },
        "parameters": {
          "ionizing radiation energy": "",
          "absorbed radiation dose rate": "",
          "exposure duration": "",
          "ionizing radiation categorized by source": "",
          "ionizing radiation device": ""
        },
        "comments": {}
      },
      {
        "sample_name": "GSM575958 extract 1",
        "characteristics": {
          "Organism": "Homo sapiens",
          "Material Type": "Whole Blood",
          "Donor": "MNs1",
          "Sex": "Male",
          "age": "29"
        },
        "factors": {
          "Smoking Status": "non-smoker",
          "Ionizing Radiation": "cesium-137 gamma radiation",
          "Absorbed Radiation Dose": "2"
        },
        "parameters": {
          "ionizing radiation energy": "0.662",
          "absorbed radiation dose rate": "0.82",
          "exposure duration": "2.44",
          "ionizing radiation categorized by source": "gamma irradiator",
          "ionizing radiation device": "Gammacell 40"
        },
        "comments": {}
      },
      {
        "sample_name": "GSM575931 extract 1",
        "characteristics": {
          "Organism": "Homo sapiens",
          "Material Type": "Whole Blood",
          "Donor": "FNs6",
          "Sex": "Female",
          "age": "21"
        },
        "factors": {
          "Smoking Status": "non-smoker",
          "Ionizing Radiation": "cesium-137 gamma radiation",
          "Absorbed Radiation Dose": "2"
        },
        "parameters": {
          "ionizing radiation energy": "0.662",
          "absorbed radiation dose rate": "0.82",
          "exposure duration": "2.44",
          "ionizing radiation categorized by source": "gamma irradiator",
          "ionizing radiation device": "Gammacell 40"
        },
        "comments": {}
      },
      {
        "sample_name": "GSM575948 extract 1",
        "characteristics": {
          "Organism": "Homo sapiens",
          "Material Type": "Whole Blood",
          "Donor": "FSm5",
          "Sex": "Female",
          "age": "29"
        },
        "factors": {
          "Smoking Status": "smoker",
          "Ionizing Radiation": "cesium-137 gamma radiation",
          "Absorbed Radiation Dose": "0.1"
        },
        "parameters": {
          "ionizing radiation energy": "0.662",
          "absorbed radiation dose rate": "0.82",
          "exposure duration": "0.12",
          "ionizing radiation categorized by source": "gamma irradiator",
          "ionizing radiation device": "Gammacell 40"
        },
        "comments": {}
      },
      {
        "sample_name": "GSM575928 extract 1",
        "characteristics": {
          "Organism": "Homo sapiens",
          "Material Type": "Whole Blood",
          "Donor": "FNs6",
          "Sex": "Female",
          "age": "21"
        },
        "factors": {
          "Smoking Status": "non-smoker",
          "Ionizing Radiation": "cesium-137 gamma radiation",
          "Absorbed Radiation Dose": "0.1"
        },
        "parameters": {
          "ionizing radiation energy": "0.662",
          "absorbed radiation dose rate": "0.82",
          "exposure duration": "0.12",
          "ionizing radiation categorized by source": "gamma irradiator",
          "ionizing radiation device": "Gammacell 40"
        },
        "comments": {}
      },
      {
        "sample_name": "GSM575961 extract 1",
        "characteristics": {
          "Organism": "Homo sapiens",
          "Material Type": "Whole Blood",
          "Donor": "MNs2",
          "Sex": "Male",
          "age": "38"
        },
        "factors": {
          "Smoking Status": "non-smoker",
          "Ionizing Radiation": "sham-irradiated",
          "Absorbed Radiation Dose": "0"
        },
        "parameters": {
          "ionizing radiation energy": "",
          "absorbed radiation dose rate": "",
          "exposure duration": "",
          "ionizing radiation categorized by source": "",
          "ionizing radiation device": ""
        },
        "comments": {}
      },
      {
        "sample_name": "GSM575950 extract 1",
        "characteristics": {
          "Organism": "Homo sapiens",
          "Material Type": "Whole Blood",
          "Donor": "FSm5",
          "Sex": "Female",
          "age": "29"
        },
        "factors": {
          "Smoking Status": "smoker",
          "Ionizing Radiation": "sham-irradiated",
          "Absorbed Radiation Dose": "0"
        },
        "parameters": {
          "ionizing radiation energy": "",
          "absorbed radiation dose rate": "",
          "exposure duration": "",
          "ionizing radiation categorized by source": "",
          "ionizing radiation device": ""
        },
        "comments": {}
      },
      {
        "sample_name": "GSM575998 extract 1",
        "characteristics": {
          "Organism": "Homo sapiens",
          "Material Type": "Whole Blood",
          "Donor": "MSm5",
          "Sex": "Male",
          "age": "59"
        },
        "factors": {
          "Smoking Status": "smoker",
          "Ionizing Radiation": "cesium-137 gamma radiation",
          "Absorbed Radiation Dose": "2"
        },
        "parameters": {
          "ionizing radiation energy": "0.662",
          "absorbed radiation dose rate": "0.82",
          "exposure duration": "2.44",
          "ionizing radiation categorized by source": "gamma irradiator",
          "ionizing radiation device": "Gammacell 40"
        },
        "comments": {}
      },
      {
        "sample_name": "GSM575970 extract 1",
        "characteristics": {
          "Organism": "Homo sapiens",
          "Material Type": "Whole Blood",
          "Donor": "MNs4",
          "Sex": "Male",
          "age": "52"
        },
        "factors": {
          "Smoking Status": "non-smoker",
          "Ionizing Radiation": "cesium-137 gamma radiation",
          "Absorbed Radiation Dose": "2"
        },
        "parameters": {
          "ionizing radiation energy": "0.662",
          "absorbed radiation dose rate": "0.82",
          "exposure duration": "2.44",
          "ionizing radiation categorized by source": "gamma irradiator",
          "ionizing radiation device": "Gammacell 40"
        },
        "comments": {}
      },
      {
        "sample_name": "GSM575988 extract 1",
        "characteristics": {
          "Organism": "Homo sapiens",
          "Material Type": "Whole Blood",
          "Donor": "MSm3",
          "Sex": "Male",
          "age": "52"
        },
        "factors": {
          "Smoking Status": "smoker",
          "Ionizing Radiation": "cesium-137 gamma radiation",
          "Absorbed Radiation Dose": "0.5"
        },
        "parameters": {
          "ionizing radiation energy": "0.662",
          "absorbed radiation dose rate": "0.82",
          "exposure duration": "0.61",
          "ionizing radiation categorized by source": "gamma irradiator",
          "ionizing radiation device": "Gammacell 40"
        },
        "comments": {}
      },
      {
        "sample_name": "GSM575953 extract 1",
        "characteristics": {
          "Organism": "Homo sapiens",
          "Material Type": "Whole Blood",
          "Donor": "FSm6",
          "Sex": "Female",
          "age": "54"
        },
        "factors": {
          "Smoking Status": "smoker",
          "Ionizing Radiation": "cesium-137 gamma radiation",
          "Absorbed Radiation Dose": "0.5"
        },
        "parameters": {
          "ionizing radiation energy": "0.662",
          "absorbed radiation dose rate": "0.82",
          "exposure duration": "0.61",
          "ionizing radiation categorized by source": "gamma irradiator",
          "ionizing radiation device": "Gammacell 40"
        },
        "comments": {}
      },
      {
        "sample_name": "GSM575979 extract 1",
        "characteristics": {
          "Organism": "Homo sapiens",
          "Material Type": "Whole Blood",
          "Donor": "MSm1",
          "Sex": "Male",
          "age": "41"
        },
        "factors": {
          "Smoking Status": "smoker",
          "Ionizing Radiation": "cesium-137 gamma radiation",
          "Absorbed Radiation Dose": "0.1"
        },
        "parameters": {
          "ionizing radiation energy": "0.662",
          "absorbed radiation dose rate": "0.82",
          "exposure duration": "0.12",
          "ionizing radiation categorized by source": "gamma irradiator",
          "ionizing radiation device": "Gammacell 40"
        },
        "comments": {}
      },
      {
        "sample_name": "GSM575941 extract 1",
        "characteristics": {
          "Organism": "Homo sapiens",
          "Material Type": "Whole Blood",
          "Donor": "FSm3",
          "Sex": "Female",
          "age": "27"
        },
        "factors": {
          "Smoking Status": "smoker",
          "Ionizing Radiation": "cesium-137 gamma radiation",
          "Absorbed Radiation Dose": "0.5"
        },
        "parameters": {
          "ionizing radiation energy": "0.662",
          "absorbed radiation dose rate": "0.82",
          "exposure duration": "0.61",
          "ionizing radiation categorized by source": "gamma irradiator",
          "ionizing radiation device": "Gammacell 40"
        },
        "comments": {}
      },
      {
        "sample_name": "GSM575936 extract 1",
        "characteristics": {
          "Organism": "Homo sapiens",
          "Material Type": "Whole Blood",
          "Donor": "FSm2",
          "Sex": "Female",
          "age": "35"
        },
        "factors": {
          "Smoking Status": "smoker",
          "Ionizing Radiation": "cesium-137 gamma radiation",
          "Absorbed Radiation Dose": "0.1"
        },
        "parameters": {
          "ionizing radiation energy": "0.662",
          "absorbed radiation dose rate": "0.82",
          "exposure duration": "0.12",
          "ionizing radiation categorized by source": "gamma irradiator",
          "ionizing radiation device": "Gammacell 40"
        },
        "comments": {}
      },
      {
        "sample_name": "GSM575954 extract 1",
        "characteristics": {
          "Organism": "Homo sapiens",
          "Material Type": "Whole Blood",
          "Donor": "FSm6",
          "Sex": "Female",
          "age": "54"
        },
        "factors": {
          "Smoking Status": "smoker",
          "Ionizing Radiation": "sham-irradiated",
          "Absorbed Radiation Dose": "0"
        },
        "parameters": {
          "ionizing radiation energy": "",
          "absorbed radiation dose rate": "",
          "exposure duration": "",
          "ionizing radiation categorized by source": "",
          "ionizing radiation device": ""
        },
        "comments": {}
      },
      {
        "sample_name": "GSM575987 extract 1",
        "characteristics": {
          "Organism": "Homo sapiens",
          "Material Type": "Whole Blood",
          "Donor": "MSm3",
          "Sex": "Male",
          "age": "52"
        },
        "factors": {
          "Smoking Status": "smoker",
          "Ionizing Radiation": "cesium-137 gamma radiation",
          "Absorbed Radiation Dose": "0.1"
        },
        "parameters": {
          "ionizing radiation energy": "0.662",
          "absorbed radiation dose rate": "0.82",
          "exposure duration": "0.12",
          "ionizing radiation categorized by source": "gamma irradiator",
          "ionizing radiation device": "Gammacell 40"
        },
        "comments": {}
      },
      {
        "sample_name": "GSM575986 extract 1",
        "characteristics": {
          "Organism": "Homo sapiens",
          "Material Type": "Whole Blood",
          "Donor": "MSm2",
          "Sex": "Male",
          "age": "31"
        },
        "factors": {
          "Smoking Status": "smoker",
          "Ionizing Radiation": "cesium-137 gamma radiation",
          "Absorbed Radiation Dose": "2"
        },
        "parameters": {
          "ionizing radiation energy": "0.662",
          "absorbed radiation dose rate": "0.82",
          "exposure duration": "2.44",
          "ionizing radiation categorized by source": "gamma irradiator",
          "ionizing radiation device": "Gammacell 40"
        },
        "comments": {}
      },
      {
        "sample_name": "GSM575922 extract 1",
        "characteristics": {
          "Organism": "Homo sapiens",
          "Material Type": "Whole Blood",
          "Donor": "FNs4",
          "Sex": "Female",
          "age": "39"
        },
        "factors": {
          "Smoking Status": "non-smoker",
          "Ionizing Radiation": "sham-irradiated",
          "Absorbed Radiation Dose": "0"
        },
        "parameters": {
          "ionizing radiation energy": "",
          "absorbed radiation dose rate": "",
          "exposure duration": "",
          "ionizing radiation categorized by source": "",
          "ionizing radiation device": ""
        },
        "comments": {}
      },
      {
        "sample_name": "GSM575972 extract 1",
        "characteristics": {
          "Organism": "Homo sapiens",
          "Material Type": "Whole Blood",
          "Donor": "MNs5",
          "Sex": "Male",
          "age": "23"
        },
        "factors": {
          "Smoking Status": "non-smoker",
          "Ionizing Radiation": "cesium-137 gamma radiation",
          "Absorbed Radiation Dose": "0.5"
        },
        "parameters": {
          "ionizing radiation energy": "0.662",
          "absorbed radiation dose rate": "0.82",
          "exposure duration": "0.61",
          "ionizing radiation categorized by source": "gamma irradiator",
          "ionizing radiation device": "Gammacell 40"
        },
        "comments": {}
      },
      {
        "sample_name": "GSM576002 extract 1",
        "characteristics": {
          "Organism": "Homo sapiens",
          "Material Type": "Whole Blood",
          "Donor": "MSm6",
          "Sex": "Male",
          "age": "64"
        },
        "factors": {
          "Smoking Status": "smoker",
          "Ionizing Radiation": "cesium-137 gamma radiation",
          "Absorbed Radiation Dose": "2"
        },
        "parameters": {
          "ionizing radiation energy": "0.662",
          "absorbed radiation dose rate": "0.82",
          "exposure duration": "2.44",
          "ionizing radiation categorized by source": "gamma irradiator",
          "ionizing radiation device": "Gammacell 40"
        },
        "comments": {}
      },
      {
        "sample_name": "GSM575975 extract 1",
        "characteristics": {
          "Organism": "Homo sapiens",
          "Material Type": "Whole Blood",
          "Donor": "MNs6",
          "Sex": "Male",
          "age": "41"
        },
        "factors": {
          "Smoking Status": "non-smoker",
          "Ionizing Radiation": "cesium-137 gamma radiation",
          "Absorbed Radiation Dose": "0.1"
        },
        "parameters": {
          "ionizing radiation energy": "0.662",
          "absorbed radiation dose rate": "0.82",
          "exposure duration": "0.12",
          "ionizing radiation categorized by source": "gamma irradiator",
          "ionizing radiation device": "Gammacell 40"
        },
        "comments": {}
      },
      {
        "sample_name": "GSM575943 extract 1",
        "characteristics": {
          "Organism": "Homo sapiens",
          "Material Type": "Whole Blood",
          "Donor": "FSm3",
          "Sex": "Female",
          "age": "27"
        },
        "factors": {
          "Smoking Status": "smoker",
          "Ionizing Radiation": "cesium-137 gamma radiation",
          "Absorbed Radiation Dose": "2"
        },
        "parameters": {
          "ionizing radiation energy": "0.662",
          "absorbed radiation dose rate": "0.82",
          "exposure duration": "2.44",
          "ionizing radiation categorized by source": "gamma irradiator",
          "ionizing radiation device": "Gammacell 40"
        },
        "comments": {}
      },
      {
        "sample_name": "GSM575927 extract 1",
        "characteristics": {
          "Organism": "Homo sapiens",
          "Material Type": "Whole Blood",
          "Donor": "FNs5",
          "Sex": "Female",
          "age": "40"
        },
        "factors": {
          "Smoking Status": "non-smoker",
          "Ionizing Radiation": "cesium-137 gamma radiation",
          "Absorbed Radiation Dose": "2"
        },
        "parameters": {
          "ionizing radiation energy": "0.662",
          "absorbed radiation dose rate": "0.82",
          "exposure duration": "2.44",
          "ionizing radiation categorized by source": "gamma irradiator",
          "ionizing radiation device": "Gammacell 40"
        },
        "comments": {}
      },
      {
        "sample_name": "GSM575937 extract 1",
        "characteristics": {
          "Organism": "Homo sapiens",
          "Material Type": "Whole Blood",
          "Donor": "FSm2",
          "Sex": "Female",
          "age": "35"
        },
        "factors": {
          "Smoking Status": "smoker",
          "Ionizing Radiation": "cesium-137 gamma radiation",
          "Absorbed Radiation Dose": "0.5"
        },
        "parameters": {
          "ionizing radiation energy": "0.662",
          "absorbed radiation dose rate": "0.82",
          "exposure duration": "0.61",
          "ionizing radiation categorized by source": "gamma irradiator",
          "ionizing radiation device": "Gammacell 40"
        },
        "comments": {}
      },
      {
        "sample_name": "GSM575949 extract 1",
        "characteristics": {
          "Organism": "Homo sapiens",
          "Material Type": "Whole Blood",
          "Donor": "FSm5",
          "Sex": "Female",
          "age": "29"
        },
        "factors": {
          "Smoking Status": "smoker",
          "Ionizing Radiation": "cesium-137 gamma radiation",
          "Absorbed Radiation Dose": "0.5"
        },
        "parameters": {
          "ionizing radiation energy": "0.662",
          "absorbed radiation dose rate": "0.82",
          "exposure duration": "0.61",
          "ionizing radiation categorized by source": "gamma irradiator",
          "ionizing radiation device": "Gammacell 40"
        },
        "comments": {}
      },
      {
        "sample_name": "GSM575921 extract 1",
        "characteristics": {
          "Organism": "Homo sapiens",
          "Material Type": "Whole Blood",
          "Donor": "FNs4",
          "Sex": "Female",
          "age": "39"
        },
        "factors": {
          "Smoking Status": "non-smoker",
          "Ionizing Radiation": "cesium-137 gamma radiation",
          "Absorbed Radiation Dose": "0.5"
        },
        "parameters": {
          "ionizing radiation energy": "0.662",
          "absorbed radiation dose rate": "0.82",
          "exposure duration": "0.61",
          "ionizing radiation categorized by source": "gamma irradiator",
          "ionizing radiation device": "Gammacell 40"
        },
        "comments": {}
      },
      {
        "sample_name": "GSM575978 extract 1",
        "characteristics": {
          "Organism": "Homo sapiens",
          "Material Type": "Whole Blood",
          "Donor": "MNs6",
          "Sex": "Male",
          "age": "41"
        },
        "factors": {
          "Smoking Status": "non-smoker",
          "Ionizing Radiation": "cesium-137 gamma radiation",
          "Absorbed Radiation Dose": "2"
        },
        "parameters": {
          "ionizing radiation energy": "0.662",
          "absorbed radiation dose rate": "0.82",
          "exposure duration": "2.44",
          "ionizing radiation categorized by source": "gamma irradiator",
          "ionizing radiation device": "Gammacell 40"
        },
        "comments": {}
      },
      {
        "sample_name": "GSM575946 extract 1",
        "characteristics": {
          "Organism": "Homo sapiens",
          "Material Type": "Whole Blood",
          "Donor": "FSm4",
          "Sex": "Female",
          "age": "55"
        },
        "factors": {
          "Smoking Status": "smoker",
          "Ionizing Radiation": "sham-irradiated",
          "Absorbed Radiation Dose": "0"
        },
        "parameters": {
          "ionizing radiation energy": "",
          "absorbed radiation dose rate": "",
          "exposure duration": "",
          "ionizing radiation categorized by source": "",
          "ionizing radiation device": ""
        },
        "comments": {}
      },
      {
        "sample_name": "GSM575968 extract 1",
        "characteristics": {
          "Organism": "Homo sapiens",
          "Material Type": "Whole Blood",
          "Donor": "MNs4",
          "Sex": "Male",
          "age": "52"
        },
        "factors": {
          "Smoking Status": "non-smoker",
          "Ionizing Radiation": "cesium-137 gamma radiation",
          "Absorbed Radiation Dose": "0.5"
        },
        "parameters": {
          "ionizing radiation energy": "0.662",
          "absorbed radiation dose rate": "0.82",
          "exposure duration": "0.61",
          "ionizing radiation categorized by source": "gamma irradiator",
          "ionizing radiation device": "Gammacell 40"
        },
        "comments": {}
      },
      {
        "sample_name": "GSM575956 extract 1",
        "characteristics": {
          "Organism": "Homo sapiens",
          "Material Type": "Whole Blood",
          "Donor": "MNs1",
          "Sex": "Male",
          "age": "29"
        },
        "factors": {
          "Smoking Status": "non-smoker",
          "Ionizing Radiation": "cesium-137 gamma radiation",
          "Absorbed Radiation Dose": "0.5"
        },
        "parameters": {
          "ionizing radiation energy": "0.662",
          "absorbed radiation dose rate": "0.82",
          "exposure duration": "0.61",
          "ionizing radiation categorized by source": "gamma irradiator",
          "ionizing radiation device": "Gammacell 40"
        },
        "comments": {}
      },
      {
        "sample_name": "GSM575909 extract 1",
        "characteristics": {
          "Organism": "Homo sapiens",
          "Material Type": "Whole Blood",
          "Donor": "FNs1",
          "Sex": "Female",
          "age": "24"
        },
        "factors": {
          "Smoking Status": "non-smoker",
          "Ionizing Radiation": "cesium-137 gamma radiation",
          "Absorbed Radiation Dose": "0.5"
        },
        "parameters": {
          "ionizing radiation energy": "0.662",
          "absorbed radiation dose rate": "0.82",
          "exposure duration": "0.61",
          "ionizing radiation categorized by source": "gamma irradiator",
          "ionizing radiation device": "Gammacell 40"
        },
        "comments": {}
      }
    ]
  },
  "assays": [
    {
      "type": "transcription-profiling",
      "platform": "",
      "qc": {},
      "library": {},
      "files": {
        "raw": [],
        "processed": [
          "GLDS-155_microarray_E-GEOD-23515.processed.1.zip",
          "GSM576002 extract 1",
          "GeneLab microarray data processing protocol",
          "GSM576002 LE 1",
          "Cy3",
          "GSM576002",
          "AGILENT WholeGenome 4x44k v1",
          "GLDS-155_microarray_GSM576002.txt",
          "GSM576002_sample_table.txt norm",
          "GLDS-155_array_raw_intensities_GLmicroarray.csv",
          "GLDS-155_array_normalized_expression_GLmicroarray.csv",
          "GLDS-155_array_SampleTable_GLmicroarray.csv",
          "GLDS-155_array_contrasts_GLmicroarray.csv",
          "GLDS-155_array_differential_expression_GLmicroarray.csv",
          "GSM576001 extract 1",
          "GSM576001 LE 1",
          "GSM576001",
          "GLDS-155_microarray_GSM576001.txt",
          "GSM576001_sample_table.txt norm",
          "GSM576000 extract 1",
          "GSM576000 LE 1",
          "GSM576000",
          "GLDS-155_microarray_GSM576000.txt",
          "GSM576000_sample_table.txt norm",
          "GSM575999 extract 1",
          "GSM575999 LE 1",
          "GSM575999",
          "GLDS-155_microarray_GSM575999.txt",
          "GSM575999_sample_table.txt norm",
          "GSM575998 extract 1",
          "GSM575998 LE 1",
          "GSM575998",
          "GLDS-155_microarray_GSM575998.txt",
          "GSM575998_sample_table.txt norm",
          "GSM575997 extract 1",
          "GSM575997 LE 1",
          "GSM575997",
          "GLDS-155_microarray_GSM575997.txt",
          "GSM575997_sample_table.txt norm",
          "GSM575996 extract 1",
          "GSM575996 LE 1",
          "GSM575996",
          "GLDS-155_microarray_GSM575996.txt",
          "GSM575996_sample_table.txt norm",
          "GSM575995 extract 1",
          "GSM575995 LE 1",
          "GSM575995",
          "GLDS-155_microarray_GSM575995.txt",
          "GSM575995_sample_table.txt norm",
          "GSM575994 extract 1",
          "GSM575994 LE 1",
          "GSM575994",
          "GLDS-155_microarray_GSM575994.txt",
          "GSM575994_sample_table.txt norm",
          "GSM575993 extract 1",
          "GSM575993 LE 1",
          "GSM575993",
          "GLDS-155_microarray_GSM575993.txt",
          "GSM575993_sample_table.txt norm",
          "GSM575992 extract 1",
          "GSM575992 LE 1",
          "GSM575992",
          "GLDS-155_microarray_GSM575992.txt",
          "GSM575992_sample_table.txt norm",
          "GSM575991 extract 1",
          "GSM575991 LE 1",
          "GSM575991",
          "GLDS-155_microarray_GSM575991.txt",
          "GSM575991_sample_table.txt norm",
          "GSM575990 extract 1",
          "GSM575990 LE 1",
          "GSM575990",
          "GLDS-155_microarray_GSM575990.txt",
          "GSM575990_sample_table.txt norm",
          "GSM575989 extract 1",
          "GSM575989 LE 1",
          "GSM575989",
          "GLDS-155_microarray_GSM575989.txt",
          "GSM575989_sample_table.txt norm",
          "GSM575988 extract 1",
          "GSM575988 LE 1",
          "GSM575988",
          "GLDS-155_microarray_GSM575988.txt",
          "GSM575988_sample_table.txt norm",
          "GSM575987 extract 1",
          "GSM575987 LE 1",
          "GSM575987",
          "GLDS-155_microarray_GSM575987.txt",
          "GSM575987_sample_table.txt norm",
          "GSM575986 extract 1",
          "GSM575986 LE 1",
          "GSM575986",
          "GLDS-155_microarray_GSM575986.txt",
          "GSM575986_sample_table.txt norm",
          "GSM575985 extract 1",
          "GSM575985 LE 1",
          "GSM575985",
          "GLDS-155_microarray_GSM575985.txt",
          "GSM575985_sample_table.txt norm",
          "GSM575984 extract 1",
          "GSM575984 LE 1",
          "GSM575984",
          "GLDS-155_microarray_GSM575984.txt",
          "GSM575984_sample_table.txt norm",
          "GSM575983 extract 1",
          "GSM575983 LE 1",
          "GSM575983",
          "GLDS-155_microarray_GSM575983.txt",
          "GSM575983_sample_table.txt norm",
          "GSM575982 extract 1",
          "GSM575982 LE 1",
          "GSM575982",
          "GLDS-155_microarray_GSM575982.txt",
          "GSM575982_sample_table.txt norm",
          "GSM575981 extract 1",
          "GSM575981 LE 1",
          "GSM575981",
          "GLDS-155_microarray_GSM575981.txt",
          "GSM575981_sample_table.txt norm",
          "GSM575980 extract 1",
          "GSM575980 LE 1",
          "GSM575980",
          "GLDS-155_microarray_GSM575980.txt",
          "GSM575980_sample_table.txt norm",
          "GSM575979 extract 1",
          "GSM575979 LE 1",
          "GSM575979",
          "GLDS-155_microarray_GSM575979.txt",
          "GSM575979_sample_table.txt norm",
          "GSM575978 extract 1",
          "GSM575978 LE 1",
          "GSM575978",
          "GLDS-155_microarray_GSM575978.txt",
          "GSM575978_sample_table.txt norm",
          "GSM575977 extract 1",
          "GSM575977 LE 1",
          "GSM575977",
          "GLDS-155_microarray_GSM575977.txt",
          "GSM575977_sample_table.txt norm",
          "GSM575976 extract 1",
          "GSM575976 LE 1",
          "GSM575976",
          "GLDS-155_microarray_GSM575976.txt",
          "GSM575976_sample_table.txt norm",
          "GSM575975 extract 1",
          "GSM575975 LE 1",
          "GSM575975",
          "GLDS-155_microarray_GSM575975.txt",
          "GSM575975_sample_table.txt norm",
          "GSM575974 extract 1",
          "GSM575974 LE 1",
          "GSM575974",
          "GLDS-155_microarray_GSM575974.txt",
          "GSM575974_sample_table.txt norm",
          "GSM575973 extract 1",
          "GSM575973 LE 1",
          "GSM575973",
          "GLDS-155_microarray_GSM575973.txt",
          "GSM575973_sample_table.txt norm",
          "GSM575972 extract 1",
          "GSM575972 LE 1",
          "GSM575972",
          "GLDS-155_microarray_GSM575972.txt",
          "GSM575972_sample_table.txt norm",
          "GSM575971 extract 1",
          "GSM575971 LE 1",
          "GSM575971",
          "GLDS-155_microarray_GSM575971.txt",
          "GSM575971_sample_table.txt norm",
          "GSM575970 extract 1",
          "GSM575970 LE 1",
          "GSM575970",
          "GLDS-155_microarray_GSM575970.txt",
          "GSM575970_sample_table.txt norm",
          "GSM575969 extract 1",
          "GSM575969 LE 1",
          "GSM575969",
          "GLDS-155_microarray_GSM575969.txt",
          "GSM575969_sample_table.txt norm",
          "GSM575968 extract 1",
          "GSM575968 LE 1",
          "GSM575968",
          "GLDS-155_microarray_GSM575968.txt",
          "GSM575968_sample_table.txt norm",
          "GSM575967 extract 1",
          "GSM575967 LE 1",
          "GSM575967",
          "GLDS-155_microarray_GSM575967.txt",
          "GSM575967_sample_table.txt norm",
          "GSM575966 extract 1",
          "GSM575966 LE 1",
          "GSM575966",
          "GLDS-155_microarray_GSM575966.txt",
          "GSM575966_sample_table.txt norm",
          "GSM575965 extract 1",
          "GSM575965 LE 1",
          "GSM575965",
          "GLDS-155_microarray_GSM575965.txt",
          "GSM575965_sample_table.txt norm",
          "GSM575964 extract 1",
          "GSM575964 LE 1",
          "GSM575964",
          "GLDS-155_microarray_GSM575964.txt",
          "GSM575964_sample_table.txt norm",
          "GSM575963 extract 1",
          "GSM575963 LE 1",
          "GSM575963",
          "GLDS-155_microarray_GSM575963.txt",
          "GSM575963_sample_table.txt norm",
          "GSM575962 extract 1",
          "GSM575962 LE 1",
          "GSM575962",
          "GLDS-155_microarray_GSM575962.txt",
          "GSM575962_sample_table.txt norm",
          "GSM575961 extract 1",
          "GSM575961 LE 1",
          "GSM575961",
          "GLDS-155_microarray_GSM575961.txt",
          "GSM575961_sample_table.txt norm",
          "GSM575960 extract 1",
          "GSM575960 LE 1",
          "GSM575960",
          "GLDS-155_microarray_GSM575960.txt",
          "GSM575960_sample_table.txt norm",
          "GSM575959 extract 1",
          "GSM575959 LE 1",
          "GSM575959",
          "GLDS-155_microarray_GSM575959.txt",
          "GSM575959_sample_table.txt norm",
          "GSM575958 extract 1",
          "GSM575958 LE 1",
          "GSM575958",
          "GLDS-155_microarray_GSM575958.txt",
          "GSM575958_sample_table.txt norm",
          "GSM575957 extract 1",
          "GSM575957 LE 1",
          "GSM575957",
          "GLDS-155_microarray_GSM575957.txt",
          "GSM575957_sample_table.txt norm",
          "GSM575956 extract 1",
          "GSM575956 LE 1",
          "GSM575956",
          "GLDS-155_microarray_GSM575956.txt",
          "GSM575956_sample_table.txt norm",
          "GSM575955 extract 1",
          "GSM575955 LE 1",
          "GSM575955",
          "GLDS-155_microarray_GSM575955.txt",
          "GSM575955_sample_table.txt norm",
          "GSM575954 extract 1",
          "GSM575954 LE 1",
          "GSM575954",
          "GLDS-155_microarray_GSM575954.txt",
          "GSM575954_sample_table.txt norm",
          "GSM575953 extract 1",
          "GSM575953 LE 1",
          "GSM575953",
          "GLDS-155_microarray_GSM575953.txt",
          "GSM575953_sample_table.txt norm",
          "GSM575952 extract 1",
          "GSM575952 LE 1",
          "GSM575952",
          "GLDS-155_microarray_GSM575952.txt",
          "GSM575952_sample_table.txt norm",
          "GSM575951 extract 1",
          "GSM575951 LE 1",
          "GSM575951",
          "GLDS-155_microarray_GSM575951.txt",
          "GSM575951_sample_table.txt norm",
          "GSM575950 extract 1",
          "GSM575950 LE 1",
          "GSM575950",
          "GLDS-155_microarray_GSM575950.txt",
          "GSM575950_sample_table.txt norm",
          "GSM575949 extract 1",
          "GSM575949 LE 1",
          "GSM575949",
          "GLDS-155_microarray_GSM575949.txt",
          "GSM575949_sample_table.txt norm",
          "GSM575948 extract 1",
          "GSM575948 LE 1",
          "GSM575948",
          "GLDS-155_microarray_GSM575948.txt",
          "GSM575948_sample_table.txt norm",
          "GSM575947 extract 1",
          "GSM575947 LE 1",
          "GSM575947",
          "GLDS-155_microarray_GSM575947.txt",
          "GSM575947_sample_table.txt norm",
          "GSM575946 extract 1",
          "GSM575946 LE 1",
          "GSM575946",
          "GLDS-155_microarray_GSM575946.txt",
          "GSM575946_sample_table.txt norm",
          "GSM575945 extract 1",
          "GSM575945 LE 1",
          "GSM575945",
          "GLDS-155_microarray_GSM575945.txt",
          "GSM575945_sample_table.txt norm",
          "GSM575944 extract 1",
          "GSM575944 LE 1",
          "GSM575944",
          "GLDS-155_microarray_GSM575944.txt",
          "GSM575944_sample_table.txt norm",
          "GSM575943 extract 1",
          "GSM575943 LE 1",
          "GSM575943",
          "GLDS-155_microarray_GSM575943.txt",
          "GSM575943_sample_table.txt norm",
          "GSM575942 extract 1",
          "GSM575942 LE 1",
          "GSM575942",
          "GLDS-155_microarray_GSM575942.txt",
          "GSM575942_sample_table.txt norm",
          "GSM575941 extract 1",
          "GSM575941 LE 1",
          "GSM575941",
          "GLDS-155_microarray_GSM575941.txt",
          "GSM575941_sample_table.txt norm",
          "GSM575940 extract 1",
          "GSM575940 LE 1",
          "GSM575940",
          "GLDS-155_microarray_GSM575940.txt",
          "GSM575940_sample_table.txt norm",
          "GSM575939 extract 1",
          "GSM575939 LE 1",
          "GSM575939",
          "GLDS-155_microarray_GSM575939.txt",
          "GSM575939_sample_table.txt norm",
          "GSM575938 extract 1",
          "GSM575938 LE 1",
          "GSM575938",
          "GLDS-155_microarray_GSM575938.txt",
          "GSM575938_sample_table.txt norm",
          "GSM575937 extract 1",
          "GSM575937 LE 1",
          "GSM575937",
          "GLDS-155_microarray_GSM575937.txt",
          "GSM575937_sample_table.txt norm",
          "GSM575936 extract 1",
          "GSM575936 LE 1",
          "GSM575936",
          "GLDS-155_microarray_GSM575936.txt",
          "GSM575936_sample_table.txt norm",
          "GSM575935 extract 1",
          "GSM575935 LE 1",
          "GSM575935",
          "GLDS-155_microarray_GSM575935.txt",
          "GSM575935_sample_table.txt norm",
          "GSM575934 extract 1",
          "GSM575934 LE 1",
          "GSM575934",
          "GLDS-155_microarray_GSM575934.txt",
          "GSM575934_sample_table.txt norm",
          "GSM575933 extract 1",
          "GSM575933 LE 1",
          "GSM575933",
          "GLDS-155_microarray_GSM575933.txt",
          "GSM575933_sample_table.txt norm",
          "GSM575932 extract 1",
          "GSM575932 LE 1",
          "GSM575932",
          "GLDS-155_microarray_GSM575932.txt",
          "GSM575932_sample_table.txt norm",
          "GSM575931 extract 1",
          "GSM575931 LE 1",
          "GSM575931",
          "GLDS-155_microarray_GSM575931.txt",
          "GSM575931_sample_table.txt norm",
          "GSM575930 extract 1",
          "GSM575930 LE 1",
          "GSM575930",
          "GLDS-155_microarray_GSM575930.txt",
          "GSM575930_sample_table.txt norm",
          "GSM575929 extract 1",
          "GSM575929 LE 1",
          "GSM575929",
          "GLDS-155_microarray_GSM575929.txt",
          "GSM575929_sample_table.txt norm",
          "GSM575928 extract 1",
          "GSM575928 LE 1",
          "GSM575928",
          "GLDS-155_microarray_GSM575928.txt",
          "GSM575928_sample_table.txt norm",
          "GSM575927 extract 1",
          "GSM575927 LE 1",
          "GSM575927",
          "GLDS-155_microarray_GSM575927.txt",
          "GSM575927_sample_table.txt norm",
          "GSM575926 extract 1",
          "GSM575926 LE 1",
          "GSM575926",
          "GLDS-155_microarray_GSM575926.txt",
          "GSM575926_sample_table.txt norm",
          "GSM575925 extract 1",
          "GSM575925 LE 1",
          "GSM575925",
          "GLDS-155_microarray_GSM575925.txt",
          "GSM575925_sample_table.txt norm",
          "GSM575924 extract 1",
          "GSM575924 LE 1",
          "GSM575924",
          "GLDS-155_microarray_GSM575924.txt",
          "GSM575924_sample_table.txt norm",
          "GSM575923 extract 1",
          "GSM575923 LE 1",
          "GSM575923",
          "GLDS-155_microarray_GSM575923.txt",
          "GSM575923_sample_table.txt norm",
          "GSM575922 extract 1",
          "GSM575922 LE 1",
          "GSM575922",
          "GLDS-155_microarray_GSM575922.txt",
          "GSM575922_sample_table.txt norm",
          "GSM575921 extract 1",
          "GSM575921 LE 1",
          "GSM575921",
          "GLDS-155_microarray_GSM575921.txt",
          "GSM575921_sample_table.txt norm",
          "GSM575920 extract 1",
          "GSM575920 LE 1",
          "GSM575920",
          "GLDS-155_microarray_GSM575920.txt",
          "GSM575920_sample_table.txt norm",
          "GSM575919 extract 1",
          "GSM575919 LE 1",
          "GSM575919",
          "GLDS-155_microarray_GSM575919.txt",
          "GSM575919_sample_table.txt norm",
          "GSM575918 extract 1",
          "GSM575918 LE 1",
          "GSM575918",
          "GLDS-155_microarray_GSM575918.txt",
          "GSM575918_sample_table.txt norm",
          "GSM575917 extract 1",
          "GSM575917 LE 1",
          "GSM575917",
          "GLDS-155_microarray_GSM575917.txt",
          "GSM575917_sample_table.txt norm",
          "GSM575916 extract 1",
          "GSM575916 LE 1",
          "GSM575916",
          "GLDS-155_microarray_GSM575916.txt",
          "GSM575916_sample_table.txt norm",
          "GSM575915 extract 1",
          "GSM575915 LE 1",
          "GSM575915",
          "GLDS-155_microarray_GSM575915.txt",
          "GSM575915_sample_table.txt norm",
          "GSM575914 extract 1",
          "GSM575914 LE 1",
          "GSM575914",
          "GLDS-155_microarray_GSM575914.txt",
          "GSM575914_sample_table.txt norm",
          "GSM575913 extract 1",
          "GSM575913 LE 1",
          "GSM575913",
          "GLDS-155_microarray_GSM575913.txt",
          "GSM575913_sample_table.txt norm",
          "GSM575912 extract 1",
          "GSM575912 LE 1",
          "GSM575912",
          "GLDS-155_microarray_GSM575912.txt",
          "GSM575912_sample_table.txt norm",
          "GSM575911 extract 1",
          "GSM575911 LE 1",
          "GSM575911",
          "GLDS-155_microarray_GSM575911.txt",
          "GSM575911_sample_table.txt norm",
          "GSM575910 extract 1",
          "GSM575910 LE 1",
          "GSM575910",
          "GLDS-155_microarray_GSM575910.txt",
          "GSM575910_sample_table.txt norm",
          "GSM575909 extract 1",
          "GSM575909 LE 1",
          "GSM575909",
          "GLDS-155_microarray_GSM575909.txt",
          "GSM575909_sample_table.txt norm",
          "GSM575908 extract 1",
          "GSM575908 LE 1",
          "GSM575908",
          "GLDS-155_microarray_GSM575908.txt",
          "GSM575908_sample_table.txt norm"
        ],
        "reports": []
      }
    }
  ]
}